stix_shifter_modules/azure_sentinel/__init__.py
stix_shifter_modules/azure_sentinel/entry_point.py
stix_shifter_modules/azure_sentinel/configuration/config.json
stix_shifter_modules/azure_sentinel/configuration/dialects.json
stix_shifter_modules/azure_sentinel/configuration/lang_en.json
stix_shifter_modules/azure_sentinel/stix_translation/__init__.py
stix_shifter_modules/azure_sentinel/stix_translation/json_to_stix_translator.py
stix_shifter_modules/azure_sentinel/stix_translation/query_constructor.py
stix_shifter_modules/azure_sentinel/stix_translation/query_translator.py
stix_shifter_modules/azure_sentinel/stix_translation/json/alertV2_from_stix_map.json
stix_shifter_modules/azure_sentinel/stix_translation/json/alert_from_stix_map.json
stix_shifter_modules/azure_sentinel/stix_translation/json/operators.json
stix_shifter_modules/azure_sentinel/stix_translation/json/to_stix_map.json
stix_shifter_modules/azure_sentinel/stix_translation/json/stix_2_1/alertV2_from_stix_map.json
stix_shifter_modules/azure_sentinel/stix_translation/json/stix_2_1/alert_from_stix_map.json
stix_shifter_modules/azure_sentinel/stix_translation/json/stix_2_1/to_stix_map.json
stix_shifter_modules/azure_sentinel/stix_transmission/__init__.py
stix_shifter_modules/azure_sentinel/stix_transmission/api_client.py
stix_shifter_modules/azure_sentinel/stix_transmission/connector.py
stix_shifter_modules/azure_sentinel/stix_transmission/error_mapper.py
stix_shifter_modules_azure_sentinel-8.0.2.dist-info/licenses/AUTHORS.md
stix_shifter_modules_azure_sentinel-8.0.2.dist-info/licenses/LICENSE.md
stix_shifter_modules_azure_sentinel-8.0.2.dist-info/licenses/NOTICE
stix_shifter_modules_azure_sentinel-8.0.2.dist-info/METADATA
stix_shifter_modules_azure_sentinel-8.0.2.dist-info/WHEEL
stix_shifter_modules_azure_sentinel-8.0.2.dist-info/top_level.txt
stix_shifter_modules_azure_sentinel-8.0.2.dist-info/RECORD
